pybtex_author_year_label/__init__.py
pybtex_author_year_label-1.0.0.dist-info/entry_points.txt
pybtex_author_year_label-1.0.0.dist-info/LICENSE
pybtex_author_year_label-1.0.0.dist-info/WHEEL
pybtex_author_year_label-1.0.0.dist-info/METADATA
pybtex_author_year_label-1.0.0.dist-info/RECORD
